azure_data_scraper_pkg_test/__init__.py
azure_data_scraper_pkg_test/audit_scope_scraper.py
azure_data_scraper_pkg_test/data_joiner.py
azure_data_scraper_pkg_test/data_mapping.py
azure_data_scraper_pkg_test/product_by_region_scraper.py
azure_data_scraper_pkg_test-0.1.2.dist-info/WHEEL
azure_data_scraper_pkg_test-0.1.2.dist-info/METADATA
azure_data_scraper_pkg_test-0.1.2.dist-info/RECORD
